pymgrit/__init__.py
pymgrit/advection/__init__.py
pymgrit/advection/advection_1d.py
pymgrit/allen_cahn/__init__.py
pymgrit/allen_cahn/allen_cahn.py
pymgrit/arenstorf_orbit/__init__.py
pymgrit/arenstorf_orbit/arenstorf_orbit.py
pymgrit/brusselator/__init__.py
pymgrit/brusselator/brusselator.py
pymgrit/core/__init__.py
pymgrit/core/application.py
pymgrit/core/at_mgrit.py
pymgrit/core/grid_transfer.py
pymgrit/core/grid_transfer_copy.py
pymgrit/core/mgrit.py
pymgrit/core/mgrit_with_plots.py
pymgrit/core/simple_setup_problem.py
pymgrit/core/split.py
pymgrit/core/vector.py
pymgrit/dahlquist/__init__.py
pymgrit/dahlquist/dahlquist.py
pymgrit/firedrake/__init__.py
pymgrit/firedrake/burgers_firedrake.py
pymgrit/firedrake/diffusion_2d_firedrake.py
pymgrit/firedrake/vector_firedrake.py
pymgrit/heat/__init__.py
pymgrit/heat/heat_1d.py
pymgrit/heat/heat_1d_2pts_bdf1.py
pymgrit/heat/heat_1d_2pts_bdf2.py
pymgrit/heat/heat_2d.py
pymgrit/heat/vector_heat_1d_2pts.py
pymgrit/induction_machine/__init__.py
pymgrit/induction_machine/grid_transfer_machine.py
pymgrit/induction_machine/helper.py
pymgrit/induction_machine/induction_machine.py
pymgrit/induction_machine/mgrit_machine.py
pymgrit/induction_machine/mgrit_machine_conv_jl.py
pymgrit/induction_machine/vector_machine.py
pymgrit/petsc/__init__.py
pymgrit/petsc/gray_scott_2d_petsc.py
pymgrit/petsc/heat_2D_petsc.py
pymgrit/petsc/vector_petsc.py
pymgrit-1.0.6.dist-info/LICENSE.rst
pymgrit-1.0.6.dist-info/METADATA
pymgrit-1.0.6.dist-info/WHEEL
pymgrit-1.0.6.dist-info/top_level.txt
pymgrit-1.0.6.dist-info/RECORD
