Metadata-Version: 2.1
Name: pymgrit
Version: 1.0.6
Summary: Python implementation of the MGRIT algorithm
Home-page: https://github.com/pymgrit/pymgrit
Author: Jens Hahne <jens.hahne@math.uni-wuppertal.de>, Stephanie Friedhoff <friedhoff@math.uni-wuppertal.de>
Author-email: jens.hahne@math.uni-wuppertal.de
License: MIT
Platform: UNKNOWN
Requires-Python: >=3.6
License-File: LICENSE.rst
Requires-Dist: numpy (>=1.17.0)
Requires-Dist: scipy (>=1.4.1)
Requires-Dist: mpi4py (>=3.0)
Requires-Dist: matplotlib (>=3.1.3)
Provides-Extra: docs
Requires-Dist: sphinx ; extra == 'docs'
Provides-Extra: tests
Requires-Dist: tox ; extra == 'tests'
